MANIFEST.in
README.txt
setup.py
collective/__init__.py
collective.subscribe.egg-info/PKG-INFO
collective.subscribe.egg-info/SOURCES.txt
collective.subscribe.egg-info/dependency_links.txt
collective.subscribe.egg-info/entry_points.txt
collective.subscribe.egg-info/namespace_packages.txt
collective.subscribe.egg-info/not-zip-safe
collective.subscribe.egg-info/requires.txt
collective.subscribe.egg-info/top_level.txt
collective/subscribe/README.txt
collective/subscribe/__init__.py
collective/subscribe/catalog.py
collective/subscribe/index.py
collective/subscribe/interfaces.py
collective/subscribe/keys.py
collective/subscribe/subscriber.py
collective/subscribe/utils.py
collective/subscribe/tests/__init__.py
collective/subscribe/tests/common.py
collective/subscribe/tests/test_catalog.py
collective/subscribe/tests/test_index.py
collective/subscribe/tests/test_keys.py
collective/subscribe/tests/test_readme.py
collective/subscribe/tests/test_subscriber.py
docs/COPYING.txt
docs/HISTORY.txt