Metadata-Version: 1.0
Name: collective.subscribe
Version: 0.1
Summary: Components relating principals/users to content items.
Home-page: https://github.com/collective/collective.subscribe
Author: Sean Upton
Author-email: sean.upton@hsc.utah.edu
License: MIT
Platform: UNKNOWN
Classifier: Programming Language :: Python
Classifier: Framework :: ZODB
Classifier: Framework :: Zope3
Classifier: Framework :: Plone
Classifier: Intended Audience :: Developers
Classifier: Development Status :: 3 - Alpha
Classifier: License :: OSI Approved :: MIT License
